{
  "data": [
    {
      "title1": "Hosting Offer Poster",
      "title2": "Hosting Offer Poster",
      "img1": "graphics-design-img-01.png",
      "img2": "graphics-design-img-02.png"
    },
    {
      "title1": "Hosting Offer Poster",
      "title2": "Hosting Offer Poster",
      "img1": "graphics-design-img-03.png",
      "img2": "graphics-design-img-04.png"
    },
    {
      "title1": "Hosting Offer Poster",
      "title2": "Hosting Offer Poster",
      "img1": "graphics-design-img-05.png",
      "img2": "graphics-design-img-06.png"
    },
    {
      "title1": "Hosting Offer Poster",
      "title2": "Hosting Offer Poster",
      "img1": "graphics-design-img-07.png",
      "img2": "graphics-design-img-08.png"
    },
    {
      "title1": "Hosting Offer Poster",
      "title2": "Hosting Offer Poster",
      "img1": "graphics-design-img-09.png",
      "img2": "graphics-design-img-10.png"
    }
  ]
}
